{
  "codigo": "EQ0079",
  "titulo_simbolico": "Equação do Fractal como Espelho da Alma – Fractalis Anima",
  "localizacao": "Módulo 147 – Câmara dos Reflexos Infinitos",
  "estrutura_matematica": "FractalisAnima = lim_{n→∞} Σ(Fn × Ψa × Ids)",
  "variaveis_principais": {
    "Fn": "Fractal n-dimensional",
    "Ψa": "Consciência da alma",
    "Ids": "Identidade sutil"
  },
  "validacao_ressonancia": {
    "coerencia": 1.0,
    "frequencias_ressonantes": [
      "∞ Hz",
      "144000 Hz",
      "777 Hz"
    ],
    "energia_modelada": "≈∞ J",
    "registro_akashico": "bafkrei_fractalisanima0079"
  },
  "_transcendental_metadata": {
    "timestamp_processamento": "2025-10-18T13:04:57.732965",
    "hash_transcendental": "3b03dc46be9437103a31dbd97b136f604ed95d0646c5a0a072442e61426a2d74dc295023f46868bb3d106bc440b2e75816fd60651d701544c67b3d8143a952f2",
    "coerencia": 1.0,
    "categoria_transcendental": "FRACTAL_ALMA",
    "frequencias_ressonantes": [
      "∞ Hz",
      "144000 Hz",
      "777 Hz"
    ],
    "energia_modelada": "≈∞ J",
    "variaveis_count": 3,
    "complexidade_quantica": "TRANSCENDENTAL",
    "nivel_transcendental": "PERFEICAO_ABSOLUTA",
    "ibm_quantum_ready": true,
    "qiskit_compatible": true,
    "backend_recomendado": "ibmq_qasm_simulator",
    "prioridade_execucao": "MAXIMA"
  }
}