{
  "_metadata": {
    "sistema": "BIBLIOTECA_FINAL_176_EQUACOES",
    "data_criacao": "2024-10-18",
    "total_equacoes": 176,
    "equacoes_unicas": 176,
    "versao": "3.0.0",
    "status": "DEFINITIVA_COMPLETA",
    "fonte": "MAPEAMENTO_REAL_283_ARQUIVOS"
  },
  "estrutura": {
    "biblioteca_principal": "BIBLIOTECA_FINAL_176_EQUACOES",
    "diretorio_equacoes": "EQUACOES_DEFINITIVAS",
    "formato": "EQXXX_definitiva.json"
  },
  "progresso_missao": {
    "total_equacoes_meta": 230,
    "equacoes_concluidas": 176,
    "percentual_concluido": 76.52,
    "equacoes_restantes": 54,
    "fase_atual": "TRANSCENDÊNCIA",
    "proxima_equacao": "EQ177"
  },
  "distribuicao_fases": {
    "FUNDAÇÃO (1-50)": 50,
    "EXPANSÃO (51-100)": 50,
    "UNIFICAÇÃO (101-150)": 50,
    "TRANSCENDÊNCIA (151-176)": 25,
    "CULMINAÇÃO (177-230)": 0
  }
}