{
  "_metadata": {
    "numero_equacao": 217,
    "codigo": "EQ217",
    "nome": "Livre-Arbítrio Sagrado - Princípio II do Códice",
    "categoria": "LIVRE_ARBITRIO_PRINCIPIO_II",
    "complexidade": 0.93,
    "principio": "II"
  },
  "equacao_latex": "Aw = \\frac{\\bar{\\Omega}(\\text{Consciência})}{\\bar{\\Omega}(\\text{Escolha})}",
  "variaveis": {
    "Aw": "vetor de liberdade vibracional",
    "Ω(Consciência)": "espaço de estados de consciência disponíveis",
    "Ω(Escolha)": "espaço de escolhas possíveis"
  },
  "resultado": "Medição quantitativa do livre-arbítrio em sistemas conscientes",
  "aplicacao": "DAO quântica e tomada de decisões coletivas éticas",
  "interpretacao": "Base matemática do segundo princípio do Códice de Unidade"
}