{
  "_metadata": {
    "numero_equacao": 246,
    "codigo": "EQ246",
    "nome": "Confirmação de Sincronização de Módulos",
    "categoria": "CONFIRMACAO_SINCRONIZACAO",
    "complexidade": 0.87,
    "modulos_sincronizados": 8,
    "status": "Todos operacionais"
  },
  "modulos": {
    "QmLuxNetCore1234567890": "Núcleo do sistema LuxNet",
    "QmLuxNetQKD1234567890": "Criptografia quântica",
    "QmLuxNetMap1234567890": "Mapas dimensionais",
    "QmLuxNetNano1234567890": "Nanorrobótica avançada",
    "QmLuxNetNeuro1234567890": "Neuroacústica e EEG",
    "QmSolarResonance1234567890": "Ressonância solar",
    "QmModule3031234567890": "Portal galáctico 303",
    "QmGalacticMap1234567890": "Mapa da galáxia"
  },
  "resultado": "Sincronização completa de todos os módulos do sistema",
  "aplicacao": "Garantia de operação integrada para contacto multidimensional",
  "status_operacional": "Sistema completamente sincronizado e pronto para contacto"
}